{
	"name": "The Vast Cold",
	"type": "feature",
	"img": "modules/nim-plus-package/assets/features/shadowmancer/pact-of-the-void/the-vast-cold.webp",
	"system": {
		"macro": "",
		"identifier": "the-vast-cold",
		"rules": [],
		"activation": {
			"acquireTargetsFromTemplate": false,
			"cost": {
				"details": "",
				"quantity": 1,
				"type": "none",
				"isReaction": false
			},
			"duration": {
				"details": "",
				"quantity": 1,
				"type": "none"
			},
			"effects": [],
			"showDescription": true,
			"targets": {
				"count": 1,
				"restrictions": ""
			},
			"template": {
				"length": 1,
				"radius": 1,
				"shape": "",
				"width": 1
			}
		},
		"description": "<p>Your minions inflict the Slowed condition when attacked in melee.</p>",
		"featureType": "class",
		"class": "shadowmancer",
		"group": "pact-of-the-void",
		"gainedAtLevels": [
			7
		],
		"selectionCountByLevel": {},
		"subclass": true
	},
	"effects": [],
	"flags": {},
	"_stats": {
		"coreVersion": "13",
		"systemId": "nimble",
		"systemVersion": "0.8.4",
		"createdTime": null,
		"modifiedTime": null,
		"lastModifiedBy": null
	},
	"_id": "6rv5EJBvMMUX4TN3",
	"folder": "0cdd37a0287b8460"
}